universities/__init__.py
universities/api.py
universities/models.py
universities-1.1.0.dist-info/LICENSE
universities-1.1.0.dist-info/METADATA
universities-1.1.0.dist-info/WHEEL
universities-1.1.0.dist-info/top_level.txt
universities-1.1.0.dist-info/RECORD
